{
  "annotations": {
    "list": [
      {
        "builtIn": 1,
        "datasource": {
          "type": "grafana",
          "uid": "-- Grafana --"
        },
        "enable": true,
        "hide": true,
        "iconColor": "rgba(0, 211, 255, 1)",
        "name": "Annotations & Alerts",
        "target": {
          "limit": 100,
          "matchAny": false,
          "tags": [],
          "type": "dashboard"
        },
        "type": "dashboard"
      }
    ]
  },
  "editable": true,
  "fiscalYearStartMonth": 0,
  "graphTooltip": 0,
  "id": 2,
  "links": [],
  "liveNow": false,
  "panels": [
    {
      "datasource": {
        "type": "influxdb",
        "uid": "vZUzYK2Vk"
      },
      "fieldConfig": {
        "defaults": {
          "color": {
            "mode": "palette-classic"
          },
          "custom": {
            "axisCenteredZero": false,
            "axisColorMode": "text",
            "axisLabel": "",
            "axisPlacement": "auto",
            "barAlignment": 0,
            "drawStyle": "line",
            "fillOpacity": 0,
            "gradientMode": "none",
            "hideFrom": {
              "legend": false,
              "tooltip": false,
              "viz": false
            },
            "lineInterpolation": "linear",
            "lineWidth": 1,
            "pointSize": 5,
            "scaleDistribution": {
              "type": "linear"
            },
            "showPoints": "auto",
            "spanNulls": false,
            "stacking": {
              "group": "A",
              "mode": "none"
            },
            "thresholdsStyle": {
              "mode": "off"
            }
          },
          "mappings": [],
          "thresholds": {
            "mode": "absolute",
            "steps": [
              {
                "color": "green",
                "value": null
              },
              {
                "color": "red",
                "value": 80
              }
            ]
          }
        },
        "overrides": []
      },
      "gridPos": {
        "h": 16,
        "w": 24,
        "x": 0,
        "y": 0
      },
      "id": 2,
      "options": {
        "legend": {
          "calcs": [],
          "displayMode": "list",
          "placement": "bottom",
          "showLegend": true
        },
        "tooltip": {
          "mode": "single",
          "sort": "none"
        }
      },
      "targets": [
        {
          "datasource": {
            "type": "influxdb",
            "uid": "vZUzYK2Vk"
          },
          "groupBy": [
            {
              "params": [
                "1s"
              ],
              "type": "time"
            },
            {
              "params": [
                "none"
              ],
              "type": "fill"
            }
          ],
          "hide": false,
          "measurement": "iot",
          "orderByTime": "ASC",
          "policy": "default",
          "refId": "DATA",
          "resultFormat": "time_series",
          "select": [
            [
              {
                "params": [
                  "*"
                ],
                "type": "field"
              },
              {
                "params": [],
                "type": "mean"
              }
            ]
          ],
          "tags": []
        }
      ],
      "title": "Grafic Date",
      "transformations": [
        {
          "id": "renameByRegex",
          "options": {
            "regex": "iot\\.mean_(.+)\\.(.+)\\.(.+)",
            "renamePattern": "$2.$3"
          }
        }
      ],
      "type": "timeseries"
    },
    {
      "datasource": {
        "type": "influxdb",
        "uid": "vZUzYK2Vk"
      },
      "description": "",
      "fieldConfig": {
        "defaults": {
          "color": {
            "mode": "thresholds"
          },
          "custom": {
            "align": "auto",
            "displayMode": "auto",
            "inspect": false
          },
          "mappings": [],
          "thresholds": {
            "mode": "absolute",
            "steps": [
              {
                "color": "green",
                "value": null
              },
              {
                "color": "red",
                "value": 80
              }
            ]
          }
        },
        "overrides": []
      },
      "gridPos": {
        "h": 16,
        "w": 24,
        "x": 0,
        "y": 16
      },
      "id": 4,
      "options": {
        "footer": {
          "enablePagination": true,
          "fields": "",
          "reducer": [
            "sum"
          ],
          "show": false
        },
        "frameIndex": 1,
        "showHeader": true
      },
      "pluginVersion": "9.3.2",
      "targets": [
        {
          "datasource": {
            "type": "influxdb",
            "uid": "vZUzYK2Vk"
          },
          "groupBy": [
            {
              "params": [
                "1s"
              ],
              "type": "time"
            },
            {
              "params": [
                "none"
              ],
              "type": "fill"
            }
          ],
          "measurement": "iot",
          "orderByTime": "ASC",
          "policy": "default",
          "refId": "A",
          "resultFormat": "table",
          "select": [
            [
              {
                "params": [
                  "*"
                ],
                "type": "field"
              },
              {
                "params": [],
                "type": "mean"
              }
            ]
          ],
          "tags": []
        }
      ],
      "title": "Tabel",
      "transformations": [
        {
          "id": "renameByRegex",
          "options": {
            "regex": "mean_(.+)\\.(.+)\\.(.+)",
            "renamePattern": "$2.$3"
          }
        }
      ],
      "transparent": true,
      "type": "table"
    }
  ],
  "refresh": "30s",
  "schemaVersion": 37,
  "style": "dark",
  "tags": [],
  "templating": {
    "list": []
  },
  "time": {
    "from": "now-6h",
    "to": "now"
  },
  "timepicker": {
    "refresh_intervals": [
      "30s"
    ]
  },
  "timezone": "",
  "title": "UPB IoT Data",
  "uid": "h96tPK24k",
  "version": 3,
  "weekStart": ""
}
